tst_monant/__init__.py
tst_monant/badatel.py
tst_monant-0.1.3.dist-info/METADATA
tst_monant-0.1.3.dist-info/WHEEL
tst_monant-0.1.3.dist-info/top_level.txt
tst_monant-0.1.3.dist-info/RECORD
