Metadata-Version: 2.1
Name: tst-monant
Version: 0.1.3
Summary: Demo library
Home-page: https://tst-monant-web-monitoring.readthedocs.io/
Author: Tomas Sako
Author-email: tomas.sako@kinit.sk
License: MIT
Platform: UNKNOWN
Classifier: Intended Audience :: Developers
Classifier: License :: OSI Approved :: MIT License
Classifier: Programming Language :: Python
Classifier: Programming Language :: Python :: 3
Classifier: Programming Language :: Python :: 3.6
Classifier: Programming Language :: Python :: 3.7
Classifier: Programming Language :: Python :: 3.8
Classifier: Programming Language :: Python :: 3.9
Classifier: Operating System :: OS Independent
Requires-Dist: beautifulsoup4
Requires-Dist: celery
